{
  "Anonymous - Open Contacts" : {
    "transaction" : "Anonymous - Open Contacts",
    "sampleCount" : 692,
    "errorCount" : 671,
    "errorPct" : 96.96532,
    "meanResTime" : 533.0346820809244,
    "medianResTime" : 113.5,
    "minResTime" : 0.0,
    "maxResTime" : 10018.0,
    "pct1ResTime" : 175.0,
    "pct2ResTime" : 188.35000000000002,
    "pct3ResTime" : 10004.0,
    "throughput" : 0.19395825637133252,
    "receivedKBytesPerSec" : 0.2198762721678591,
    "sentKBytesPerSec" : 0.09075753434630743
  },
  "Editor - Login" : {
    "transaction" : "Editor - Login",
    "sampleCount" : 34,
    "errorCount" : 32,
    "errorPct" : 94.117645,
    "meanResTime" : 661.470588235294,
    "medianResTime" : 80.5,
    "minResTime" : 6.0,
    "maxResTime" : 10010.0,
    "pct1ResTime" : 160.5,
    "pct2ResTime" : 10006.25,
    "pct3ResTime" : 10010.0,
    "throughput" : 0.00979691852335081,
    "receivedKBytesPerSec" : 0.02284418762871062,
    "sentKBytesPerSec" : 0.01463909953064116
  },
  "Anonymous - Open Predefined Date" : {
    "transaction" : "Anonymous - Open Predefined Date",
    "sampleCount" : 4145,
    "errorCount" : 4025,
    "errorPct" : 97.10494,
    "meanResTime" : 523.9256936067572,
    "medianResTime" : 114.0,
    "minResTime" : 0.0,
    "maxResTime" : 10017.0,
    "pct1ResTime" : 176.0,
    "pct2ResTime" : 189.0,
    "pct3ResTime" : 10004.0,
    "throughput" : 1.1538552544953729,
    "receivedKBytesPerSec" : 1.5214098368770193,
    "sentKBytesPerSec" : 0.5501625175200882
  },
  "Anonymous - Search by Name" : {
    "transaction" : "Anonymous - Search by Name",
    "sampleCount" : 4143,
    "errorCount" : 4028,
    "errorPct" : 97.224236,
    "meanResTime" : 528.5684286748723,
    "medianResTime" : 113.0,
    "minResTime" : 0.0,
    "maxResTime" : 10015.0,
    "pct1ResTime" : 174.0,
    "pct2ResTime" : 187.79999999999973,
    "pct3ResTime" : 10004.0,
    "throughput" : 1.1555376555220362,
    "receivedKBytesPerSec" : 1.4844338659519143,
    "sentKBytesPerSec" : 0.533706524220549
  },
  "Admin- Open Login Page" : {
    "transaction" : "Admin- Open Login Page",
    "sampleCount" : 110,
    "errorCount" : 102,
    "errorPct" : 92.72727,
    "meanResTime" : 473.98181818181854,
    "medianResTime" : 106.5,
    "minResTime" : 3.0,
    "maxResTime" : 10003.0,
    "pct1ResTime" : 174.9,
    "pct2ResTime" : 884.1499999999824,
    "pct3ResTime" : 10003.0,
    "throughput" : 0.030614360639951464,
    "receivedKBytesPerSec" : 0.026329328592282118,
    "sentKBytesPerSec" : 0.03392584297337803
  },
  "Editor - Edit Post" : {
    "transaction" : "Editor - Edit Post",
    "sampleCount" : 16,
    "errorCount" : 0,
    "errorPct" : 0.0,
    "meanResTime" : 11.0625,
    "medianResTime" : 4.0,
    "minResTime" : 2.0,
    "maxResTime" : 114.0,
    "pct1ResTime" : 39.800000000000075,
    "pct2ResTime" : 114.0,
    "pct3ResTime" : 114.0,
    "throughput" : 0.10164409320763347,
    "receivedKBytesPerSec" : 0.01806564937870048,
    "sentKBytesPerSec" : 0.1968113533275735
  },
  "Anonymous - Open Home page" : {
    "transaction" : "Anonymous - Open Home page",
    "sampleCount" : 5176,
    "errorCount" : 5026,
    "errorPct" : 97.10201,
    "meanResTime" : 528.1595826893334,
    "medianResTime" : 113.0,
    "minResTime" : 0.0,
    "maxResTime" : 10024.0,
    "pct1ResTime" : 174.0,
    "pct2ResTime" : 189.0,
    "pct3ResTime" : 10004.0,
    "throughput" : 1.4378073327062835,
    "receivedKBytesPerSec" : 1.860248741918584,
    "sentKBytesPerSec" : 0.6792636371205963
  },
  "Admin - User List" : {
    "transaction" : "Admin - User List",
    "sampleCount" : 1082,
    "errorCount" : 1013,
    "errorPct" : 93.62292,
    "meanResTime" : 511.7606284658035,
    "medianResTime" : 107.5,
    "minResTime" : 2.0,
    "maxResTime" : 10018.0,
    "pct1ResTime" : 175.0,
    "pct2ResTime" : 189.0,
    "pct3ResTime" : 10004.0,
    "throughput" : 0.3013881402931153,
    "receivedKBytesPerSec" : 0.2903044617352659,
    "sentKBytesPerSec" : 0.35796397313202727
  },
  "Admin - Login" : {
    "transaction" : "Admin - Login",
    "sampleCount" : 110,
    "errorCount" : 102,
    "errorPct" : 92.72727,
    "meanResTime" : 468.8272727272727,
    "medianResTime" : 112.0,
    "minResTime" : 6.0,
    "maxResTime" : 10009.0,
    "pct1ResTime" : 179.8,
    "pct2ResTime" : 188.0,
    "pct3ResTime" : 10008.67,
    "throughput" : 0.030628741231130605,
    "receivedKBytesPerSec" : 0.09989635738645508,
    "sentKBytesPerSec" : 0.04712622311353406
  },
  "Anonymous - Open Random Page" : {
    "transaction" : "Anonymous - Open Random Page",
    "sampleCount" : 143,
    "errorCount" : 2,
    "errorPct" : 1.3986014,
    "meanResTime" : 152.02797202797203,
    "medianResTime" : 10.0,
    "minResTime" : 6.0,
    "maxResTime" : 10001.0,
    "pct1ResTime" : 20.19999999999999,
    "pct2ResTime" : 30.799999999999983,
    "pct3ResTime" : 10001.0,
    "throughput" : 0.8144528357766918,
    "receivedKBytesPerSec" : 20.822765558612126,
    "sentKBytesPerSec" : 0.3806401214844684
  },
  "Admin - LogOut" : {
    "transaction" : "Admin - LogOut",
    "sampleCount" : 108,
    "errorCount" : 102,
    "errorPct" : 94.44444,
    "meanResTime" : 553.6018518518518,
    "medianResTime" : 112.5,
    "minResTime" : 4.0,
    "maxResTime" : 10004.0,
    "pct1ResTime" : 175.0,
    "pct2ResTime" : 5100.7499999999745,
    "pct3ResTime" : 10003.91,
    "throughput" : 0.03049346042330005,
    "receivedKBytesPerSec" : 0.060661560212019905,
    "sentKBytesPerSec" : 0.035893344039926105
  },
  "Editor -  Get Post Content" : {
    "transaction" : "Editor -  Get Post Content",
    "sampleCount" : 16,
    "errorCount" : 0,
    "errorPct" : 0.0,
    "meanResTime" : 5.187499999999999,
    "medianResTime" : 3.5,
    "minResTime" : 2.0,
    "maxResTime" : 18.0,
    "pct1ResTime" : 11.700000000000006,
    "pct2ResTime" : 18.0,
    "pct3ResTime" : 18.0,
    "throughput" : 0.10122674157445544,
    "receivedKBytesPerSec" : 0.07856440709599458,
    "sentKBytesPerSec" : 0.1314761389590095
  },
  "Anonymous - Open Random Date" : {
    "transaction" : "Anonymous - Open Random Date",
    "sampleCount" : 1385,
    "errorCount" : 1345,
    "errorPct" : 97.111916,
    "meanResTime" : 534.548014440434,
    "medianResTime" : 117.0,
    "minResTime" : 3.0,
    "maxResTime" : 10016.0,
    "pct1ResTime" : 175.0,
    "pct2ResTime" : 189.0,
    "pct3ResTime" : 10004.0,
    "throughput" : 0.38657089012343476,
    "receivedKBytesPerSec" : 0.4854252525759298,
    "sentKBytesPerSec" : 0.18421047099825164
  },
  "Editor - Open Page by Predefined Date" : {
    "transaction" : "Editor - Open Page by Predefined Date",
    "sampleCount" : 1682,
    "errorCount" : 1647,
    "errorPct" : 97.91914,
    "meanResTime" : 528.8953626634961,
    "medianResTime" : 115.0,
    "minResTime" : 2.0,
    "maxResTime" : 10012.0,
    "pct1ResTime" : 174.0,
    "pct2ResTime" : 189.8499999999999,
    "pct3ResTime" : 10004.0,
    "throughput" : 0.46808466822342387,
    "receivedKBytesPerSec" : 0.5658418257166606,
    "sentKBytesPerSec" : 0.535346184372484
  },
  "Anonymous - Open First Post" : {
    "transaction" : "Anonymous - Open First Post",
    "sampleCount" : 193,
    "errorCount" : 4,
    "errorPct" : 2.0725389,
    "meanResTime" : 248.27979274611403,
    "medianResTime" : 38.0,
    "minResTime" : 14.0,
    "maxResTime" : 10002.0,
    "pct1ResTime" : 65.0,
    "pct2ResTime" : 72.59999999999997,
    "pct3ResTime" : 10001.06,
    "throughput" : 1.098813509143495,
    "receivedKBytesPerSec" : 25.13072206779053,
    "sentKBytesPerSec" : 0.4471546939405843
  },
  "Admin - Delete User" : {
    "transaction" : "Admin - Delete User",
    "sampleCount" : 33,
    "errorCount" : 0,
    "errorPct" : 0.0,
    "meanResTime" : 7.9393939393939394,
    "medianResTime" : 6.0,
    "minResTime" : 3.0,
    "maxResTime" : 33.0,
    "pct1ResTime" : 14.400000000000006,
    "pct2ResTime" : 21.09999999999995,
    "pct3ResTime" : 33.0,
    "throughput" : 0.2061430632859204,
    "receivedKBytesPerSec" : 0.03663870851370851,
    "sentKBytesPerSec" : 0.3808205157636976
  },
  "Admin - Add User" : {
    "transaction" : "Admin - Add User",
    "sampleCount" : 1049,
    "errorCount" : 1013,
    "errorPct" : 96.56816,
    "meanResTime" : 531.0352716873206,
    "medianResTime" : 116.0,
    "minResTime" : 4.0,
    "maxResTime" : 10010.0,
    "pct1ResTime" : 177.0,
    "pct2ResTime" : 190.0,
    "pct3ResTime" : 10004.5,
    "throughput" : 0.29234135325899296,
    "receivedKBytesPerSec" : 0.1707788462047599,
    "sentKBytesPerSec" : 0.4206374959207373
  },
  "Total" : {
    "transaction" : "Total",
    "sampleCount" : 2861,
    "errorCount" : 2169,
    "errorPct" : 75.81265,
    "meanResTime" : 456.6183152743786,
    "medianResTime" : 92.0,
    "minResTime" : 0.0,
    "maxResTime" : 10018.0,
    "pct1ResTime" : 175.0,
    "pct2ResTime" : 230.70000000000027,
    "pct3ResTime" : 10004.0,
    "throughput" : 0.7949989260150824,
    "receivedKBytesPerSec" : 3.6254855031834694,
    "sentKBytesPerSec" : 0.83644781433649
  },
  "Anonymous - Open Large Calendar" : {
    "transaction" : "Anonymous - Open Large Calendar",
    "sampleCount" : 1385,
    "errorCount" : 1344,
    "errorPct" : 97.03971,
    "meanResTime" : 532.4953068592063,
    "medianResTime" : 112.0,
    "minResTime" : 0.0,
    "maxResTime" : 10011.0,
    "pct1ResTime" : 178.0,
    "pct2ResTime" : 189.0,
    "pct3ResTime" : 10004.0,
    "throughput" : 0.38668810156523525,
    "receivedKBytesPerSec" : 0.4262280396581454,
    "sentKBytesPerSec" : 0.18326623207065476
  },
  "Anonymous - Comment" : {
    "transaction" : "Anonymous - Comment",
    "sampleCount" : 64,
    "errorCount" : 3,
    "errorPct" : 4.6875,
    "meanResTime" : 805.4062499999999,
    "medianResTime" : 240.5,
    "minResTime" : 11.0,
    "maxResTime" : 10004.0,
    "pct1ResTime" : 1575.0,
    "pct2ResTime" : 1805.25,
    "pct3ResTime" : 10004.0,
    "throughput" : 0.35251802523808734,
    "receivedKBytesPerSec" : 0.8349496147088147,
    "sentKBytesPerSec" : 0.7791962984918839
  },
  "Editor - Open Random Post" : {
    "transaction" : "Editor - Open Random Post",
    "sampleCount" : 1682,
    "errorCount" : 1647,
    "errorPct" : 97.91914,
    "meanResTime" : 623.3436385255642,
    "medianResTime" : 117.0,
    "minResTime" : 0.0,
    "maxResTime" : 16596.0,
    "pct1ResTime" : 180.0,
    "pct2ResTime" : 5932.949999999997,
    "pct3ResTime" : 10004.0,
    "throughput" : 0.4680603102110056,
    "receivedKBytesPerSec" : 85.35820672106568,
    "sentKBytesPerSec" : 0.527652690762404
  },
  "Admin - Open Admin Page" : {
    "transaction" : "Admin - Open Admin Page",
    "sampleCount" : 1082,
    "errorCount" : 1011,
    "errorPct" : 93.43808,
    "meanResTime" : 504.03327171903794,
    "medianResTime" : 110.0,
    "minResTime" : 1.0,
    "maxResTime" : 10014.0,
    "pct1ResTime" : 173.70000000000005,
    "pct2ResTime" : 187.0,
    "pct3ResTime" : 10004.0,
    "throughput" : 0.30133484093586466,
    "receivedKBytesPerSec" : 0.20218302401488292,
    "sentKBytesPerSec" : 0.3356613518223517
  },
  "Editor - Open Login Page" : {
    "transaction" : "Editor - Open Login Page",
    "sampleCount" : 34,
    "errorCount" : 32,
    "errorPct" : 94.117645,
    "meanResTime" : 751.176470588235,
    "medianResTime" : 129.5,
    "minResTime" : 11.0,
    "maxResTime" : 10014.0,
    "pct1ResTime" : 1082.0,
    "pct2ResTime" : 10005.75,
    "pct3ResTime" : 10014.0,
    "throughput" : 0.00979134640804457,
    "receivedKBytesPerSec" : 0.008325569251601316,
    "sentKBytesPerSec" : 0.010687911560527511
  },
  "Anonymous - Open Random Post" : {
    "transaction" : "Anonymous - Open Random Post",
    "sampleCount" : 125,
    "errorCount" : 0,
    "errorPct" : 0.0,
    "meanResTime" : 38.919999999999995,
    "medianResTime" : 37.0,
    "minResTime" : 9.0,
    "maxResTime" : 94.0,
    "pct1ResTime" : 56.80000000000001,
    "pct2ResTime" : 69.79999999999995,
    "pct3ResTime" : 91.91999999999996,
    "throughput" : 0.7896099958308592,
    "receivedKBytesPerSec" : 18.447942098688614,
    "sentKBytesPerSec" : 0.329594316150367
  }
}